{
    "geometry": [
        {
            "controlPoints": [
                {
                    "id": 109
                },
                {
                    "id": 110
                },
                {
                    "id": 111
                },
                {
                    "id": 112
                },
                {
                    "id": 113
                },
                {
                    "id": 114
                },
                {
                    "id": 115
                },
                {
                    "id": 116
                },
                {
                    "id": 117
                },
                {
                    "id": 118
                },
                {
                    "id": 119
                },
                {
                    "id": 120
                },
                {
                    "id": 121
                },
                {
                    "id": 122
                },
                {
                    "id": 123
                },
                {
                    "id": 124
                }
            ],
            "id": 2,
            "name": "BezierSurface C0",
            "objectType": "bezierSurfaceC0",
            "samples": {
                "u": 4,
                "v": 4
            },
            "size": {
                "u": 4,
                "v": 4
            }
        },
        {
            "controlPoints": [
                {
                    "id": 125
                },
                {
                    "id": 126
                },
                {
                    "id": 127
                },
                {
                    "id": 128
                },
                {
                    "id": 129
                },
                {
                    "id": 130
                },
                {
                    "id": 131
                },
                {
                    "id": 132
                },
                {
                    "id": 133
                },
                {
                    "id": 134
                },
                {
                    "id": 135
                },
                {
                    "id": 136
                },
                {
                    "id": 137
                },
                {
                    "id": 138
                },
                {
                    "id": 139
                },
                {
                    "id": 140
                }
            ],
            "id": 105,
            "name": "BezierSurface C0",
            "objectType": "bezierSurfaceC0",
            "samples": {
                "u": 4,
                "v": 4
            },
            "size": {
                "u": 4,
                "v": 4
            }
        },
        {
            "controlPoints": [
                {
                    "id": 141
                },
                {
                    "id": 142
                },
                {
                    "id": 143
                },
                {
                    "id": 144
                },
                {
                    "id": 145
                },
                {
                    "id": 146
                },
                {
                    "id": 147
                },
                {
                    "id": 148
                },
                {
                    "id": 149
                },
                {
                    "id": 150
                },
                {
                    "id": 151
                },
                {
                    "id": 152
                },
                {
                    "id": 153
                },
                {
                    "id": 154
                },
                {
                    "id": 155
                },
                {
                    "id": 156
                }
            ],
            "id": 107,
            "name": "BezierSurface C0",
            "objectType": "bezierSurfaceC0",
            "samples": {
                "u": 4,
                "v": 4
            },
            "size": {
                "u": 4,
                "v": 4
            }
        }
    ],
    "points": [
        {
            "id": 109,
            "name": "Point 96",
            "position": {
                "x": -0.75,
                "y": 0.0,
                "z": -1.125
            }
        },
        {
            "id": 110,
            "name": "Point 97",
            "position": {
                "x": -0.75,
                "y": 0.0,
                "z": -0.375
            }
        },
        {
            "id": 111,
            "name": "Point 98",
            "position": {
                "x": -0.75,
                "y": 0.0,
                "z": 0.375
            }
        },
        {
            "id": 113,
            "name": "Point 100",
            "position": {
                "x": -0.25,
                "y": 0.0,
                "z": -1.125
            }
        },
        {
            "id": 114,
            "name": "Point 101",
            "position": {
                "x": -0.25,
                "y": 0.0,
                "z": -0.375
            }
        },
        {
            "id": 115,
            "name": "Point 102",
            "position": {
                "x": -0.25,
                "y": 0.0,
                "z": 0.375
            }
        },
        {
            "id": 116,
            "name": "Point 103",
            "position": {
                "x": -0.25,
                "y": 0.0,
                "z": 1.125
            }
        },
        {
            "id": 117,
            "name": "Point 104",
            "position": {
                "x": 0.25,
                "y": 0.0,
                "z": -1.125
            }
        },
        {
            "id": 118,
            "name": "Point 105",
            "position": {
                "x": 0.25,
                "y": 0.0,
                "z": -0.375
            }
        },
        {
            "id": 119,
            "name": "Point 106",
            "position": {
                "x": 0.25,
                "y": 0.0,
                "z": 0.375
            }
        },
        {
            "id": 120,
            "name": "Point 107",
            "position": {
                "x": 0.25,
                "y": 0.0,
                "z": 1.125
            }
        },
        {
            "id": 121,
            "name": "Point 108",
            "position": {
                "x": 0.75,
                "y": 0.0,
                "z": -1.125
            }
        },
        {
            "id": 122,
            "name": "Point 109",
            "position": {
                "x": 0.75,
                "y": 0.0,
                "z": -0.375
            }
        },
        {
            "id": 123,
            "name": "Point 110",
            "position": {
                "x": 0.75,
                "y": 0.0,
                "z": 0.375
            }
        },
        {
            "id": 124,
            "name": "Point 111",
            "position": {
                "x": 0.75,
                "y": 0.0,
                "z": 1.125
            }
        },
        {
            "id": 125,
            "name": "Point 112",
            "position": {
                "x": -0.75,
                "y": 0.0,
                "z": -1.125
            }
        },
        {
            "id": 126,
            "name": "Point 113",
            "position": {
                "x": -0.75,
                "y": 0.0,
                "z": -0.375
            }
        },
        {
            "id": 127,
            "name": "Point 114",
            "position": {
                "x": -0.75,
                "y": 0.0,
                "z": 0.375
            }
        },
        {
            "id": 128,
            "name": "Point 115",
            "position": {
                "x": -0.75,
                "y": 0.0,
                "z": 1.125
            }
        },
        {
            "id": 129,
            "name": "Point 116",
            "position": {
                "x": -0.25,
                "y": 0.0,
                "z": -1.125
            }
        },
        {
            "id": 130,
            "name": "Point 117",
            "position": {
                "x": -0.25,
                "y": 0.0,
                "z": -0.375
            }
        },
        {
            "id": 131,
            "name": "Point 118",
            "position": {
                "x": -0.25,
                "y": 0.0,
                "z": 0.375
            }
        },
        {
            "id": 132,
            "name": "Point 119",
            "position": {
                "x": -0.25,
                "y": 0.0,
                "z": 1.125
            }
        },
        {
            "id": 133,
            "name": "Point 120",
            "position": {
                "x": 0.25,
                "y": 0.0,
                "z": -1.125
            }
        },
        {
            "id": 134,
            "name": "Point 121",
            "position": {
                "x": 0.25,
                "y": 0.0,
                "z": -0.375
            }
        },
        {
            "id": 135,
            "name": "Point 122",
            "position": {
                "x": 0.25,
                "y": 0.0,
                "z": 0.375
            }
        },
        {
            "id": 136,
            "name": "Point 123",
            "position": {
                "x": 0.25,
                "y": 0.0,
                "z": 1.125
            }
        },
        {
            "id": 137,
            "name": "Point 124",
            "position": {
                "x": 0.75,
                "y": 0.0,
                "z": -1.125
            }
        },
        {
            "id": 138,
            "name": "Point 125",
            "position": {
                "x": 0.75,
                "y": 0.0,
                "z": -0.375
            }
        },
        {
            "id": 139,
            "name": "Point 126",
            "position": {
                "x": 0.75,
                "y": 0.0,
                "z": 0.375
            }
        },
        {
            "id": 140,
            "name": "Point 127",
            "position": {
                "x": 0.75,
                "y": 0.0,
                "z": 1.125
            }
        },
        {
            "id": 141,
            "name": "Point 128",
            "position": {
                "x": -0.75,
                "y": 0.0,
                "z": -1.125
            }
        },
        {
            "id": 142,
            "name": "Point 129",
            "position": {
                "x": -0.75,
                "y": 0.0,
                "z": -0.375
            }
        },
        {
            "id": 143,
            "name": "Point 130",
            "position": {
                "x": -0.75,
                "y": 0.0,
                "z": 0.375
            }
        },
        {
            "id": 144,
            "name": "Point 131",
            "position": {
                "x": -0.75,
                "y": 0.0,
                "z": 1.125
            }
        },
        {
            "id": 145,
            "name": "Point 132",
            "position": {
                "x": -0.25,
                "y": 0.0,
                "z": -1.125
            }
        },
        {
            "id": 146,
            "name": "Point 133",
            "position": {
                "x": -0.25,
                "y": 0.0,
                "z": -0.375
            }
        },
        {
            "id": 147,
            "name": "Point 134",
            "position": {
                "x": -0.25,
                "y": 0.0,
                "z": 0.375
            }
        },
        {
            "id": 148,
            "name": "Point 135",
            "position": {
                "x": -0.25,
                "y": 0.0,
                "z": 1.125
            }
        },
        {
            "id": 149,
            "name": "Point 136",
            "position": {
                "x": 0.25,
                "y": 0.0,
                "z": -1.125
            }
        },
        {
            "id": 150,
            "name": "Point 137",
            "position": {
                "x": 0.25,
                "y": 0.0,
                "z": -0.375
            }
        },
        {
            "id": 151,
            "name": "Point 138",
            "position": {
                "x": 0.25,
                "y": 0.0,
                "z": 0.375
            }
        },
        {
            "id": 152,
            "name": "Point 139",
            "position": {
                "x": 0.25,
                "y": 0.0,
                "z": 1.125
            }
        },
        {
            "id": 153,
            "name": "Point 140",
            "position": {
                "x": 0.75,
                "y": 0.0,
                "z": -1.125
            }
        },
        {
            "id": 154,
            "name": "Point 141",
            "position": {
                "x": 0.75,
                "y": 0.0,
                "z": -0.375
            }
        },
        {
            "id": 155,
            "name": "Point 142",
            "position": {
                "x": 0.75,
                "y": 0.0,
                "z": 0.375
            }
        },
        {
            "id": 156,
            "name": "Point 143",
            "position": {
                "x": 0.75,
                "y": 0.0,
                "z": 1.125
            }
        }
    ]
}