{
    "geometry": [
        {
            "controlPoints": [
                {
                    "id": 1
                },
                {
                    "id": 12
                },
                {
                    "id": 22
                },
                {
                    "id": 32
                },
                {
                    "id": 42
                },
                {
                    "id": 52
                },
                {
                    "id": 62
                },
                {
                    "id": 72
                },
                {
                    "id": 82
                },
                {
                    "id": 1
                },
                {
                    "id": 3
                },
                {
                    "id": 13
                },
                {
                    "id": 23
                },
                {
                    "id": 33
                },
                {
                    "id": 43
                },
                {
                    "id": 53
                },
                {
                    "id": 63
                },
                {
                    "id": 73
                },
                {
                    "id": 83
                },
                {
                    "id": 3
                },
                {
                    "id": 4
                },
                {
                    "id": 14
                },
                {
                    "id": 24
                },
                {
                    "id": 34
                },
                {
                    "id": 44
                },
                {
                    "id": 54
                },
                {
                    "id": 64
                },
                {
                    "id": 74
                },
                {
                    "id": 84
                },
                {
                    "id": 4
                },
                {
                    "id": 5
                },
                {
                    "id": 15
                },
                {
                    "id": 25
                },
                {
                    "id": 35
                },
                {
                    "id": 45
                },
                {
                    "id": 55
                },
                {
                    "id": 65
                },
                {
                    "id": 75
                },
                {
                    "id": 85
                },
                {
                    "id": 5
                },
                {
                    "id": 6
                },
                {
                    "id": 16
                },
                {
                    "id": 26
                },
                {
                    "id": 36
                },
                {
                    "id": 46
                },
                {
                    "id": 56
                },
                {
                    "id": 66
                },
                {
                    "id": 76
                },
                {
                    "id": 86
                },
                {
                    "id": 6
                },
                {
                    "id": 7
                },
                {
                    "id": 17
                },
                {
                    "id": 27
                },
                {
                    "id": 37
                },
                {
                    "id": 47
                },
                {
                    "id": 57
                },
                {
                    "id": 67
                },
                {
                    "id": 77
                },
                {
                    "id": 87
                },
                {
                    "id": 7
                },
                {
                    "id": 8
                },
                {
                    "id": 18
                },
                {
                    "id": 28
                },
                {
                    "id": 38
                },
                {
                    "id": 48
                },
                {
                    "id": 58
                },
                {
                    "id": 68
                },
                {
                    "id": 78
                },
                {
                    "id": 88
                },
                {
                    "id": 8
                },
                {
                    "id": 9
                },
                {
                    "id": 19
                },
                {
                    "id": 29
                },
                {
                    "id": 39
                },
                {
                    "id": 49
                },
                {
                    "id": 59
                },
                {
                    "id": 69
                },
                {
                    "id": 79
                },
                {
                    "id": 89
                },
                {
                    "id": 9
                },
                {
                    "id": 10
                },
                {
                    "id": 20
                },
                {
                    "id": 30
                },
                {
                    "id": 40
                },
                {
                    "id": 50
                },
                {
                    "id": 60
                },
                {
                    "id": 70
                },
                {
                    "id": 80
                },
                {
                    "id": 90
                },
                {
                    "id": 10
                },
                {
                    "id": 11
                },
                {
                    "id": 21
                },
                {
                    "id": 31
                },
                {
                    "id": 41
                },
                {
                    "id": 51
                },
                {
                    "id": 61
                },
                {
                    "id": 71
                },
                {
                    "id": 81
                },
                {
                    "id": 91
                },
                {
                    "id": 11
                }
            ],
            "id": 2,
            "name": "BezierSurface C0",
            "objectType": "bezierSurfaceC0",
            "samples": {
                "u": 4,
                "v": 4
            },
            "size": {
                "u": 10,
                "v": 10
            }
        }
    ],
    "points": [
        {
            "id": 1,
            "name": "Point 0",
            "position": {
                "x": 2.0,
                "y": 0.0,
                "z": 0.0
            }
        },
        {
            "id": 3,
            "name": "Point 1",
            "position": {
                "x": 2.0,
                "y": 0.30000001192092896,
                "z": 0.0
            }
        },
        {
            "id": 4,
            "name": "Point 2",
            "position": {
                "x": 2.0,
                "y": 0.6000000238418579,
                "z": 0.0
            }
        },
        {
            "id": 5,
            "name": "Point 3",
            "position": {
                "x": 2.0,
                "y": 0.9000000357627869,
                "z": 0.0
            }
        },
        {
            "id": 6,
            "name": "Point 4",
            "position": {
                "x": 2.0,
                "y": 1.2000000476837158,
                "z": 0.0
            }
        },
        {
            "id": 7,
            "name": "Point 5",
            "position": {
                "x": 2.0,
                "y": 1.5,
                "z": 0.0
            }
        },
        {
            "id": 8,
            "name": "Point 6",
            "position": {
                "x": 2.0,
                "y": 1.7999999523162842,
                "z": 0.0
            }
        },
        {
            "id": 9,
            "name": "Point 7",
            "position": {
                "x": 2.0,
                "y": 2.0999999046325684,
                "z": 0.0
            }
        },
        {
            "id": 10,
            "name": "Point 8",
            "position": {
                "x": 2.0,
                "y": 2.3999998569488525,
                "z": 0.0
            }
        },
        {
            "id": 11,
            "name": "Point 9",
            "position": {
                "x": 2.0,
                "y": 2.6999998092651367,
                "z": 0.0
            }
        },
        {
            "id": 12,
            "name": "Point 10",
            "position": {
                "x": 1.5320888757705688,
                "y": 0.0,
                "z": 1.285575270652771
            }
        },
        {
            "id": 13,
            "name": "Point 11",
            "position": {
                "x": 1.5320888757705688,
                "y": 0.30000001192092896,
                "z": 1.285575270652771
            }
        },
        {
            "id": 14,
            "name": "Point 12",
            "position": {
                "x": 1.5320888757705688,
                "y": 0.6000000238418579,
                "z": 1.285575270652771
            }
        },
        {
            "id": 15,
            "name": "Point 13",
            "position": {
                "x": 1.5320888757705688,
                "y": 0.9000000357627869,
                "z": 1.285575270652771
            }
        },
        {
            "id": 16,
            "name": "Point 14",
            "position": {
                "x": 1.5320888757705688,
                "y": 1.2000000476837158,
                "z": 1.285575270652771
            }
        },
        {
            "id": 17,
            "name": "Point 15",
            "position": {
                "x": 1.5320888757705688,
                "y": 1.5,
                "z": 1.285575270652771
            }
        },
        {
            "id": 18,
            "name": "Point 16",
            "position": {
                "x": 1.5320888757705688,
                "y": 1.7999999523162842,
                "z": 1.285575270652771
            }
        },
        {
            "id": 19,
            "name": "Point 17",
            "position": {
                "x": 1.5320888757705688,
                "y": 2.0999999046325684,
                "z": 1.285575270652771
            }
        },
        {
            "id": 20,
            "name": "Point 18",
            "position": {
                "x": 1.5320888757705688,
                "y": 2.3999998569488525,
                "z": 1.285575270652771
            }
        },
        {
            "id": 21,
            "name": "Point 19",
            "position": {
                "x": 1.5320888757705688,
                "y": 2.6999998092651367,
                "z": 1.285575270652771
            }
        },
        {
            "id": 22,
            "name": "Point 20",
            "position": {
                "x": 0.34729620814323425,
                "y": 0.0,
                "z": 1.9696155786514282
            }
        },
        {
            "id": 23,
            "name": "Point 21",
            "position": {
                "x": 0.34729620814323425,
                "y": 0.30000001192092896,
                "z": 1.9696155786514282
            }
        },
        {
            "id": 24,
            "name": "Point 22",
            "position": {
                "x": 0.34729620814323425,
                "y": 0.6000000238418579,
                "z": 1.9696155786514282
            }
        },
        {
            "id": 25,
            "name": "Point 23",
            "position": {
                "x": 0.34729620814323425,
                "y": 0.9000000357627869,
                "z": 1.9696155786514282
            }
        },
        {
            "id": 26,
            "name": "Point 24",
            "position": {
                "x": 0.34729620814323425,
                "y": 1.2000000476837158,
                "z": 1.9696155786514282
            }
        },
        {
            "id": 27,
            "name": "Point 25",
            "position": {
                "x": 0.34729620814323425,
                "y": 1.5,
                "z": 1.9696155786514282
            }
        },
        {
            "id": 28,
            "name": "Point 26",
            "position": {
                "x": 0.34729620814323425,
                "y": 1.7999999523162842,
                "z": 1.9696155786514282
            }
        },
        {
            "id": 29,
            "name": "Point 27",
            "position": {
                "x": 0.34729620814323425,
                "y": 2.0999999046325684,
                "z": 1.9696155786514282
            }
        },
        {
            "id": 30,
            "name": "Point 28",
            "position": {
                "x": 0.34729620814323425,
                "y": 2.3999998569488525,
                "z": 1.9696155786514282
            }
        },
        {
            "id": 31,
            "name": "Point 29",
            "position": {
                "x": 0.34729620814323425,
                "y": 2.6999998092651367,
                "z": 1.9696155786514282
            }
        },
        {
            "id": 32,
            "name": "Point 30",
            "position": {
                "x": -1.0000001192092896,
                "y": 0.0,
                "z": 1.7320507764816284
            }
        },
        {
            "id": 33,
            "name": "Point 31",
            "position": {
                "x": -1.0000001192092896,
                "y": 0.30000001192092896,
                "z": 1.7320507764816284
            }
        },
        {
            "id": 34,
            "name": "Point 32",
            "position": {
                "x": -1.0000001192092896,
                "y": 0.6000000238418579,
                "z": 1.7320507764816284
            }
        },
        {
            "id": 35,
            "name": "Point 33",
            "position": {
                "x": -1.0000001192092896,
                "y": 0.9000000357627869,
                "z": 1.7320507764816284
            }
        },
        {
            "id": 36,
            "name": "Point 34",
            "position": {
                "x": -1.0000001192092896,
                "y": 1.2000000476837158,
                "z": 1.7320507764816284
            }
        },
        {
            "id": 37,
            "name": "Point 35",
            "position": {
                "x": -1.0000001192092896,
                "y": 1.5,
                "z": 1.7320507764816284
            }
        },
        {
            "id": 38,
            "name": "Point 36",
            "position": {
                "x": -1.0000001192092896,
                "y": 1.7999999523162842,
                "z": 1.7320507764816284
            }
        },
        {
            "id": 39,
            "name": "Point 37",
            "position": {
                "x": -1.0000001192092896,
                "y": 2.0999999046325684,
                "z": 1.7320507764816284
            }
        },
        {
            "id": 40,
            "name": "Point 38",
            "position": {
                "x": -1.0000001192092896,
                "y": 2.3999998569488525,
                "z": 1.7320507764816284
            }
        },
        {
            "id": 41,
            "name": "Point 39",
            "position": {
                "x": -1.0000001192092896,
                "y": 2.6999998092651367,
                "z": 1.7320507764816284
            }
        },
        {
            "id": 42,
            "name": "Point 40",
            "position": {
                "x": -1.8793853521347046,
                "y": 0.0,
                "z": 0.6840400099754333
            }
        },
        {
            "id": 43,
            "name": "Point 41",
            "position": {
                "x": -1.8793853521347046,
                "y": 0.30000001192092896,
                "z": 0.6840400099754333
            }
        },
        {
            "id": 44,
            "name": "Point 42",
            "position": {
                "x": -1.8793853521347046,
                "y": 0.6000000238418579,
                "z": 0.6840400099754333
            }
        },
        {
            "id": 45,
            "name": "Point 43",
            "position": {
                "x": -1.8793853521347046,
                "y": 0.9000000357627869,
                "z": 0.6840400099754333
            }
        },
        {
            "id": 46,
            "name": "Point 44",
            "position": {
                "x": -1.8793853521347046,
                "y": 1.2000000476837158,
                "z": 0.6840400099754333
            }
        },
        {
            "id": 47,
            "name": "Point 45",
            "position": {
                "x": -1.8793853521347046,
                "y": 1.5,
                "z": 0.6840400099754333
            }
        },
        {
            "id": 48,
            "name": "Point 46",
            "position": {
                "x": -1.8793853521347046,
                "y": 1.7999999523162842,
                "z": 0.6840400099754333
            }
        },
        {
            "id": 49,
            "name": "Point 47",
            "position": {
                "x": -1.8793853521347046,
                "y": 2.0999999046325684,
                "z": 0.6840400099754333
            }
        },
        {
            "id": 50,
            "name": "Point 48",
            "position": {
                "x": -1.8793853521347046,
                "y": 2.3999998569488525,
                "z": 0.6840400099754333
            }
        },
        {
            "id": 51,
            "name": "Point 49",
            "position": {
                "x": -1.8793853521347046,
                "y": 2.6999998092651367,
                "z": 0.6840400099754333
            }
        },
        {
            "id": 52,
            "name": "Point 50",
            "position": {
                "x": -1.8793851137161255,
                "y": 0.0,
                "z": -0.6840407848358154
            }
        },
        {
            "id": 53,
            "name": "Point 51",
            "position": {
                "x": -1.8793851137161255,
                "y": 0.30000001192092896,
                "z": -0.6840407848358154
            }
        },
        {
            "id": 54,
            "name": "Point 52",
            "position": {
                "x": -1.8793851137161255,
                "y": 0.6000000238418579,
                "z": -0.6840407848358154
            }
        },
        {
            "id": 55,
            "name": "Point 53",
            "position": {
                "x": -1.8793851137161255,
                "y": 0.9000000357627869,
                "z": -0.6840407848358154
            }
        },
        {
            "id": 56,
            "name": "Point 54",
            "position": {
                "x": -1.8793851137161255,
                "y": 1.2000000476837158,
                "z": -0.6840407848358154
            }
        },
        {
            "id": 57,
            "name": "Point 55",
            "position": {
                "x": -1.8793851137161255,
                "y": 1.5,
                "z": -0.6840407848358154
            }
        },
        {
            "id": 58,
            "name": "Point 56",
            "position": {
                "x": -1.8793851137161255,
                "y": 1.7999999523162842,
                "z": -0.6840407848358154
            }
        },
        {
            "id": 59,
            "name": "Point 57",
            "position": {
                "x": -1.8793851137161255,
                "y": 2.0999999046325684,
                "z": -0.6840407848358154
            }
        },
        {
            "id": 60,
            "name": "Point 58",
            "position": {
                "x": -1.8793851137161255,
                "y": 2.3999998569488525,
                "z": -0.6840407848358154
            }
        },
        {
            "id": 61,
            "name": "Point 59",
            "position": {
                "x": -1.8793851137161255,
                "y": 2.6999998092651367,
                "z": -0.6840407848358154
            }
        },
        {
            "id": 62,
            "name": "Point 60",
            "position": {
                "x": -0.9999998211860657,
                "y": 0.0,
                "z": -1.732050895690918
            }
        },
        {
            "id": 63,
            "name": "Point 61",
            "position": {
                "x": -0.9999998211860657,
                "y": 0.30000001192092896,
                "z": -1.732050895690918
            }
        },
        {
            "id": 64,
            "name": "Point 62",
            "position": {
                "x": -0.9999998211860657,
                "y": 0.6000000238418579,
                "z": -1.732050895690918
            }
        },
        {
            "id": 65,
            "name": "Point 63",
            "position": {
                "x": -0.9999998211860657,
                "y": 0.9000000357627869,
                "z": -1.732050895690918
            }
        },
        {
            "id": 66,
            "name": "Point 64",
            "position": {
                "x": -0.9999998211860657,
                "y": 1.2000000476837158,
                "z": -1.732050895690918
            }
        },
        {
            "id": 67,
            "name": "Point 65",
            "position": {
                "x": -0.9999998211860657,
                "y": 1.5,
                "z": -1.732050895690918
            }
        },
        {
            "id": 68,
            "name": "Point 66",
            "position": {
                "x": -0.9999998211860657,
                "y": 1.7999999523162842,
                "z": -1.732050895690918
            }
        },
        {
            "id": 69,
            "name": "Point 67",
            "position": {
                "x": -0.9999998211860657,
                "y": 2.0999999046325684,
                "z": -1.732050895690918
            }
        },
        {
            "id": 70,
            "name": "Point 68",
            "position": {
                "x": -0.9999998211860657,
                "y": 2.3999998569488525,
                "z": -1.732050895690918
            }
        },
        {
            "id": 71,
            "name": "Point 69",
            "position": {
                "x": -0.9999998211860657,
                "y": 2.6999998092651367,
                "z": -1.732050895690918
            }
        },
        {
            "id": 72,
            "name": "Point 70",
            "position": {
                "x": 0.3472962975502014,
                "y": 0.0,
                "z": -1.9696154594421387
            }
        },
        {
            "id": 73,
            "name": "Point 71",
            "position": {
                "x": 0.3472962975502014,
                "y": 0.30000001192092896,
                "z": -1.9696154594421387
            }
        },
        {
            "id": 74,
            "name": "Point 72",
            "position": {
                "x": 0.3472962975502014,
                "y": 0.6000000238418579,
                "z": -1.9696154594421387
            }
        },
        {
            "id": 75,
            "name": "Point 73",
            "position": {
                "x": 0.3472962975502014,
                "y": 0.9000000357627869,
                "z": -1.9696154594421387
            }
        },
        {
            "id": 76,
            "name": "Point 74",
            "position": {
                "x": 0.3472962975502014,
                "y": 1.2000000476837158,
                "z": -1.9696154594421387
            }
        },
        {
            "id": 77,
            "name": "Point 75",
            "position": {
                "x": 0.3472962975502014,
                "y": 1.5,
                "z": -1.9696154594421387
            }
        },
        {
            "id": 78,
            "name": "Point 76",
            "position": {
                "x": 0.3472962975502014,
                "y": 1.7999999523162842,
                "z": -1.9696154594421387
            }
        },
        {
            "id": 79,
            "name": "Point 77",
            "position": {
                "x": 0.3472962975502014,
                "y": 2.0999999046325684,
                "z": -1.9696154594421387
            }
        },
        {
            "id": 80,
            "name": "Point 78",
            "position": {
                "x": 0.3472962975502014,
                "y": 2.3999998569488525,
                "z": -1.9696154594421387
            }
        },
        {
            "id": 81,
            "name": "Point 79",
            "position": {
                "x": 0.3472962975502014,
                "y": 2.6999998092651367,
                "z": -1.9696154594421387
            }
        },
        {
            "id": 82,
            "name": "Point 80",
            "position": {
                "x": 1.5320886373519897,
                "y": 0.0,
                "z": -1.28557550907135
            }
        },
        {
            "id": 83,
            "name": "Point 81",
            "position": {
                "x": 1.5320886373519897,
                "y": 0.30000001192092896,
                "z": -1.28557550907135
            }
        },
        {
            "id": 84,
            "name": "Point 82",
            "position": {
                "x": 1.5320886373519897,
                "y": 0.6000000238418579,
                "z": -1.28557550907135
            }
        },
        {
            "id": 85,
            "name": "Point 83",
            "position": {
                "x": 1.5320886373519897,
                "y": 0.9000000357627869,
                "z": -1.28557550907135
            }
        },
        {
            "id": 86,
            "name": "Point 84",
            "position": {
                "x": 1.5320886373519897,
                "y": 1.2000000476837158,
                "z": -1.28557550907135
            }
        },
        {
            "id": 87,
            "name": "Point 85",
            "position": {
                "x": 1.5320886373519897,
                "y": 1.5,
                "z": -1.28557550907135
            }
        },
        {
            "id": 88,
            "name": "Point 86",
            "position": {
                "x": 1.5320886373519897,
                "y": 1.7999999523162842,
                "z": -1.28557550907135
            }
        },
        {
            "id": 89,
            "name": "Point 87",
            "position": {
                "x": 1.5320886373519897,
                "y": 2.0999999046325684,
                "z": -1.28557550907135
            }
        },
        {
            "id": 90,
            "name": "Point 88",
            "position": {
                "x": 1.5320886373519897,
                "y": 2.3999998569488525,
                "z": -1.28557550907135
            }
        },
        {
            "id": 91,
            "name": "Point 89",
            "position": {
                "x": 1.5320886373519897,
                "y": 2.6999998092651367,
                "z": -1.28557550907135
            }
        }
    ]
}